Metadata-Version: 2.1
Name: sensorhandler
Version: 0.1.2
Summary: Multipurpose sensorhandler, read the value from source & do somethings (send, save, trigger, ...) with it, as configed.
Home-page: https://github.com/UedaTakeyuki/sensorhandler
Author: Takeyuki UEDA
Author-email: gde00107@nifty.com
License: MIT
Keywords: testing,logging,example
Platform: UNKNOWN
Classifier: Development Status :: 4 - Beta
Classifier: Programming Language :: Python
Classifier: Topic :: Terminals
